CHANGELOG.txt
LICENCE.txt
MANIFEST.in
README.txt
setup.py
DataStructures1.egg-info/PKG-INFO
DataStructures1.egg-info/SOURCES.txt
DataStructures1.egg-info/dependency_links.txt
DataStructures1.egg-info/top_level.txt
data_structure/__init__.py
data_structure/linkedlist.py
data_structure/queue.py
data_structure/search.py
data_structure/sort.py
data_structure/stack.py