Metadata-Version: 2.1
Name: DataStructures1
Version: 1.0.0
Summary: Data Structure Package
Home-page: UNKNOWN
Author: Dereck Jos
Author-email: dereckjos12@gmail.com
License: UNKNOWN
Platform: UNKNOWN
Classifier: Programming Language :: Python :: 3
Classifier: License :: OSI Approved :: MIT License
Classifier: Operating System :: OS Independent
Requires-Python: >=3.6
